jiraone/__init__.py
jiraone/access.py
jiraone/exceptions.py
jiraone/jira_logs.py
jiraone/management.py
jiraone/module.py
jiraone/reporting.py
jiraone/utils.py
jiraone-0.9.3.dist-info/licenses/LICENSE
jiraone-0.9.3.dist-info/METADATA
jiraone-0.9.3.dist-info/WHEEL
jiraone-0.9.3.dist-info/top_level.txt
jiraone-0.9.3.dist-info/RECORD
