Metadata-Version: 2.4
Name: jiraone
Version: 0.9.3
Summary: A REST API Implementation to Jira Cloud APIs for creating reports and for performing other Jira queries.
Author-email: Prince Nyeche <support@elfapp.website>
License-Expression: MIT
Project-URL: Homepage, https://github.com/princenyeche/jiraone
Project-URL: Source, https://github.com/princenyeche/jiraone
Project-URL: Documentation, https://jiraone.readthedocs.io/
Project-URL: Tracker, https://github.com/princenyeche/jiraone/issues
Classifier: Programming Language :: Python :: 3
Classifier: Operating System :: OS Independent
Requires-Python: >=3.9
License-File: LICENSE
Requires-Dist: requests
Provides-Extra: docs
Requires-Dist: sphinx; extra == "docs"
Requires-Dist: sphinxcontrib-httpdomain; extra == "docs"
Requires-Dist: jiraone; extra == "docs"
Requires-Dist: sphinx-autoapi; extra == "docs"
Requires-Dist: scipy; extra == "docs"
Requires-Dist: numpy; extra == "docs"
Requires-Dist: pandas; extra == "docs"
Requires-Dist: matplotlib; extra == "docs"
Dynamic: license-file
